codesentinel/AGENT_INSTRUCTIONS.md
codesentinel/__init__.py
codesentinel/gui_launcher.py
codesentinel/gui_project_setup.py
codesentinel/gui_wizard_v2.py
codesentinel/launcher.py
codesentinel/cli/__init__.py
codesentinel/cli/__main__.py
codesentinel/cli/agent_utils.py
codesentinel/cli/alert_utils.py
codesentinel/cli/clean_utils.py
codesentinel/cli/command_utils.py
codesentinel/cli/dev_audit_remediation.py
codesentinel/cli/dev_audit_review.py
codesentinel/cli/dev_audit_utils.py
codesentinel/cli/doc_utils.py
codesentinel/cli/document_formatter_cli.py
codesentinel/cli/memory_utils.py
codesentinel/cli/root_clean_utils.py
codesentinel/cli/scan_utils.py
codesentinel/cli/test_utils.py
codesentinel/cli/update_utils.py
codesentinel/core/__init__.py
codesentinel/core/dev_audit.py
codesentinel/gui/__init__.py
codesentinel/gui/formatting_config.py
codesentinel/utils/alerts.py
codesentinel/utils/archive_decision_provider.py
codesentinel/utils/archive_enrichment_pipeline.py
codesentinel/utils/archive_index_manager.py
codesentinel/utils/archive_maintenance_scheduler.py
codesentinel/utils/archive_verification_pipeline.py
codesentinel/utils/config.py
codesentinel/utils/document_formatter.py
codesentinel/utils/file_integrity.py
codesentinel/utils/oracl_context_tier.py
codesentinel/utils/path_resolver.py
codesentinel/utils/process_monitor.py
codesentinel/utils/root_policy.py
codesentinel/utils/scheduler.py
codesentinel/utils/session_memory.py
codesentinel/utils/versioning.py
codesentinel-1.1.2.dist-info/licenses/LICENSE
tools/verify_version.py
tools/codesentinel/AGENT_INSTRUCTIONS.md
tools/codesentinel/AGENT_INTEGRATION_IMPLEMENTATION_GUIDE.md
tools/codesentinel/clean_unicode.py
tools/codesentinel/defrag_instructions.py
tools/codesentinel/duplication_detector.py
tools/codesentinel/manage_satellites.py
tools/codesentinel/psutil_benchmark.py
tools/codesentinel/report_generator.py
tools/codesentinel/report_workflow.py
tools/codesentinel/root_cleanup.py
tools/config/reporting.json
codesentinel-1.1.2.dist-info/METADATA
codesentinel-1.1.2.dist-info/WHEEL
codesentinel-1.1.2.dist-info/entry_points.txt
codesentinel-1.1.2.dist-info/top_level.txt
codesentinel-1.1.2.dist-info/RECORD
