Metadata-Version: 2.4
Name: codesentinel
Version: 1.1.2
Summary: Automated Maintenance & Security Monitoring | A Polymath Project
Home-page: https://github.com/joediggidyyy/CodeSentinel
Author: joediggidyyy
Author-email: joediggidyyy <joediggidy3@gmail.com>
Maintainer-email: joediggidyyy <joediggidy3@gmail.com>
License: MIT
Project-URL: Homepage, https://github.com/joediggidyyy/CodeSentinel
Project-URL: Documentation, https://codesentinel.readthedocs.io/
Project-URL: Repository, https://github.com/joediggidyyy/CodeSentinel
Project-URL: Issues, https://github.com/joediggidyyy/CodeSentinel/issues
Project-URL: Changelog, https://github.com/joediggidyyy/CodeSentinel/blob/main/CHANGELOG.md
Keywords: security,monitoring,maintenance,automation,alerts
Classifier: Development Status :: 4 - Beta
Classifier: Intended Audience :: Developers
Classifier: Operating System :: OS Independent
Classifier: Programming Language :: Python :: 3
Classifier: Programming Language :: Python :: 3.8
Classifier: Programming Language :: Python :: 3.9
Classifier: Programming Language :: Python :: 3.10
Classifier: Programming Language :: Python :: 3.11
Classifier: Programming Language :: Python :: 3.12
Classifier: Programming Language :: Python :: 3.13
Classifier: Topic :: Security
Classifier: Topic :: Software Development :: Quality Assurance
Classifier: Topic :: System :: Monitoring
Requires-Python: >=3.8
License-File: LICENSE
Requires-Dist: requests>=2.25.0
Requires-Dist: schedule>=1.1.0
Requires-Dist: psutil>=5.8.0
Requires-Dist: pathlib2>=2.3.0; python_version < "3.4"
Provides-Extra: dev
Requires-Dist: pytest>=6.0.0; extra == "dev"
Requires-Dist: flake8>=3.8.0; extra == "dev"
Requires-Dist: black>=21.0.0; extra == "dev"
Requires-Dist: mypy>=0.800; extra == "dev"
Requires-Dist: sphinx>=4.0.0; extra == "dev"
Provides-Extra: gui
Provides-Extra: full
Requires-Dist: requests>=2.25.0; extra == "full"
Requires-Dist: schedule>=1.1.0; extra == "full"
Dynamic: author
Dynamic: home-page
Dynamic: license-file
Dynamic: requires-python
